whiteboxlayer/__init__.py
whiteboxlayer/layers.py
whiteboxlayer/extensions/__init__.py
whiteboxlayer/extensions/attention.py
whiteboxlayer/extensions/convolution.py
whiteboxlayer/extensions/graph.py
whiteboxlayer/extensions/losses.py
whiteboxlayer/extensions/recurrent.py
whiteboxlayer/extensions/utility.py
whiteboxlayer-0.2.9.dist-info/LICENSE
whiteboxlayer-0.2.9.dist-info/METADATA
whiteboxlayer-0.2.9.dist-info/WHEEL
whiteboxlayer-0.2.9.dist-info/top_level.txt
whiteboxlayer-0.2.9.dist-info/RECORD
