Metadata-Version: 2.1
Name: whiteboxlayer
Version: 0.2.9
Summary: TensorFlow based custom layers
Home-page: https://github.com/YeongHyeon/white-box-layer
Author: YeongHyeon Park
Author-email: young200405@gmail.com
License: UNKNOWN
Download-URL: https://github.com/YeongHyeon/white-box-layer/archive/refs/heads/master.zip
Keywords: whiteboxlayer
Platform: UNKNOWN
Classifier: Programming Language :: Python :: 3
Requires-Python: >=3
License-File: LICENSE
Requires-Dist: tensorflow (==2.8.0)
